apistar_mail/__init__.py
apistar_mail/exc.py
apistar_mail/mail.py
apistar_mail-0.3.0.dist-info/LICENSE.txt
apistar_mail-0.3.0.dist-info/METADATA
apistar_mail-0.3.0.dist-info/RECORD
apistar_mail-0.3.0.dist-info/WHEEL
apistar_mail-0.3.0.dist-info/top_level.txt
