Metadata-Version: 2.1
Name: apistar-mail
Version: 0.3.0
Summary: A simple email Component for APIStar
Home-page: https://github.com/androiddrew/apistar-mail
Author: Drew Bednar
Author-email: drew@androiddrew.com
License: BSD
Keywords: apistar-mail apistar_mail mail SMTP
Platform: UNKNOWN
Classifier: Development Status :: 2 - Pre-Alpha
Classifier: Environment :: Web Environment
Classifier: Intended Audience :: Developers
Classifier: License :: OSI Approved :: BSD License
Classifier: Natural Language :: English
Classifier: Programming Language :: Python :: 3.5
Classifier: Programming Language :: Python :: 3.6
Provides-Extra: testing
Requires-Dist: apistar (>=0.4)
Provides-Extra: testing
Requires-Dist: pytest; extra == 'testing'
Requires-Dist: pytest-cov; extra == 'testing'
Requires-Dist: tox; extra == 'testing'
